tensorflow_hs_addon/__init__.py
tensorflow_hs_addon/python/__init__.py
tensorflow_hs_addon/python/ops/__init__.py
tensorflow_hs_addon/python/ops/_reco_ops.so
tensorflow_hs_addon/python/ops/reco_ops.py
tensorflow_hs_addon/python/ops/test.py
tensorflow_hs_addon-0.0.5.dist-info/LICENSE
tensorflow_hs_addon-0.0.5.dist-info/METADATA
tensorflow_hs_addon-0.0.5.dist-info/WHEEL
tensorflow_hs_addon-0.0.5.dist-info/top_level.txt
tensorflow_hs_addon-0.0.5.dist-info/RECORD
