Metadata-Version: 2.1
Name: tensorflow-hs-addon
Version: 0.0.5
Summary: tensorflow-custom-ops is an examples for custom ops for TensorFlow
Home-page: UNKNOWN
Author: Google Inc.
Author-email: opensource@google.com
License: Apache 2.0
Keywords: tensorflow custom op machine learning
Platform: UNKNOWN
Classifier: Development Status :: 4 - Beta
Classifier: Intended Audience :: Developers
Classifier: Intended Audience :: Education
Classifier: Intended Audience :: Science/Research
Classifier: License :: OSI Approved :: Apache Software License
Classifier: Programming Language :: Python :: 2.7
Classifier: Programming Language :: Python :: 3.4
Classifier: Programming Language :: Python :: 3.5
Classifier: Programming Language :: Python :: 3.6
Classifier: Topic :: Scientific/Engineering :: Mathematics
Classifier: Topic :: Software Development :: Libraries :: Python Modules
Classifier: Topic :: Software Development :: Libraries
Requires-Dist: tensorflow>=2.5.0
